{
  "title": "Book 1 Why bother? An Intro",
  "summary": "Buddhist practice notes and teachings - buddhism-books-lama-tsomo’s-courses",
  "createdDate": "2025-12-11T18:28:30Z",
  "updatedDate": "2025-12-11T18:28:30Z",
  "hashtags": ["#buddhism", "#pre-website", "#buddhism-books-lama-tsomo’s-courses"],
  "status": "active",
  "thoughts": [
    {
      "id": "thought-buddhism-001",
      "date": "2025-12-11T18:28:30Z",
      "content": "# Book 1 Why bother? An Intro\n\n- Three essential facets of the path to enlightenment: listen, contemplate, meditate\n- “…not a religion, but a set of highly effective, proven methods for improving my mind” - Rinpoche\n- Blind faith is the least kind - my journey had to start in this very specific moment in my life because I now have the experience to understand it\n- One does not have to forsake their existing belief system; they are intrinsically Buddhist in the grand scheme of things.\n- The Dalai Lama believes that most people should seek enlightenment in the path of their own people but for some other people’s paths are more effective for them\n\nWhy I bothered…\n\n- Earthseed\n- Riusseau’s wilderness\n- Melancholic longing, existential loneliness\n- This reminds me of “hole in our souls” that all addicts struggle to fill\n- Wrong foundations for society\n- Guide through the coming “Earth change”\n- Prodigal Son moment\n- Baha’i prayers claimed her mind\n- “the Mystery” - Rabbi Herman Schaalman\n- “changing channels”\n- “the soup”\n- She had a long winding path and sudden shock to her paradigm that spurred her to pursue a spiritual path.\n-\n",
      "hashtags": ["#buddhism", "#buddhism-books-lama-tsomo’s-courses"]
    }
  ],
  "changelog": [
    {
      "date": "2025-12-11T18:28:30Z",
      "action": "created",
      "description": "Imported from Notion export - pre-website content"
    },
    {
      "date": "2025-12-11T18:28:30Z",
      "action": "thought_added",
      "description": "Added Buddhist teaching notes",
      "thoughtId": "thought-buddhism-001"
    }
  ]
}
